cyberspace/BasicMask.py
cyberspace/MaskSet.py
cyberspace/Navigator.py
cyberspace/Scraper.py
cyberspace/Skill.py
cyberspace/Web.py
cyberspace/__init__.py
cyberspace/exceptions.py
cyberspace/find_common.py
cyberspace/get_id_token.py
cyberspace/iban/CountryCodes.py
cyberspace/iban/__init__.py
cyberspace/imdb/IMDB.py
cyberspace/imdb/__init__.py
cyberspace/imdb/get_title_year_and_resolution_from_file_name.py
cyberspace/search/SearchEngine.py
cyberspace/search/SearchResults.py
cyberspace/search/__init__.py
cyberspace/search/is_yahoo_finance_search_url_function.py
cyberspace/search/bing/__init__.py
cyberspace/wikipedia/InfoBox.py
cyberspace/wikipedia/Page_helpers.py
cyberspace/wikipedia/Wikipedia.py
cyberspace/wikipedia/WikipediaPage.py
cyberspace/wikipedia/__init__.py
cyberspace/wikipedia/exceptions.py
cyberspace/wikipedia/get_special_data.py
cyberspace/wikipedia/get_wikipedia_id.py
cyberspace/wikipedia/is_wikipedia_page_url.py
cyberspace-2022.2.12.dist-info/LICENSE
cyberspace-2022.2.12.dist-info/METADATA
cyberspace-2022.2.12.dist-info/WHEEL
cyberspace-2022.2.12.dist-info/top_level.txt
cyberspace-2022.2.12.dist-info/RECORD
