Metadata-Version: 2.1
Name: cyberspace
Version: 2022.2.12
Summary: Python library for navigating the world wide web
Home-page: https://github.com/idin/cyberspace
Author: Idin
Author-email: py@idin.ca
License: MIT
Platform: UNKNOWN
Classifier: Development Status :: 3 - Alpha
Classifier: Intended Audience :: Developers
Classifier: Programming Language :: Python :: 3 :: Only
Classifier: Programming Language :: Python :: 3.6
Classifier: Programming Language :: Python :: 3.7
Classifier: Topic :: Software Development :: Libraries :: Python Modules
Requires-Python: ~=3.6
Requires-Dist: IMDbPy
Requires-Dist: bs4
Requires-Dist: requests-ntlm
Requires-Dist: pandas
Requires-Dist: requests
Requires-Dist: memoria
Requires-Dist: chronometry
Requires-Dist: slytherin
Requires-Dist: abstract
Requires-Dist: pensieve
Requires-Dist: ravenclaw
Requires-Dist: silverware
